LICENSE
README.md
pyproject.toml
requirements.in
hacca/__init__.py
hacca/alignment.py
hacca/data.py
hacca/loss.py
hacca/utils.py
hacca/version.py
hacca.egg-info/PKG-INFO
hacca.egg-info/SOURCES.txt
hacca.egg-info/dependency_links.txt
hacca.egg-info/requires.txt
hacca.egg-info/top_level.txt